edutools_github_classroom/__init__.py
edutools_github_classroom/assignments.py
edutools_github_classroom/base.py
edutools_github_classroom/classroom_api.py
edutools_github_classroom/classrooms.py
edutools_github_classroom/grades.py
edutools_github_classroom/submissions.py
edutools_github_classroom-0.1.0.dist-info/licenses/LICENSE
edutools_github_classroom-0.1.0.dist-info/METADATA
edutools_github_classroom-0.1.0.dist-info/WHEEL
edutools_github_classroom-0.1.0.dist-info/top_level.txt
edutools_github_classroom-0.1.0.dist-info/RECORD
