Metadata-Version: 2.4
Name: edutools-github-classroom
Version: 0.1.0
Summary: A Python library for interacting with the GitHub Classroom REST API
Home-page: https://github.com/najasoft/edutools-github-classroom
Author: NajaSoft
Author-email: contact@najasoft.com
Project-URL: Bug Reports, https://github.com/najasoft/edutools-github-classroom/issues
Project-URL: Source, https://github.com/najasoft/edutools-github-classroom
Project-URL: Documentation, https://github.com/najasoft/edutools-github-classroom#readme
Keywords: github classroom education api teaching grading
Classifier: Development Status :: 4 - Beta
Classifier: Intended Audience :: Education
Classifier: Intended Audience :: Developers
Classifier: License :: OSI Approved :: MIT License
Classifier: Programming Language :: Python :: 3
Classifier: Programming Language :: Python :: 3.7
Classifier: Programming Language :: Python :: 3.8
Classifier: Programming Language :: Python :: 3.9
Classifier: Programming Language :: Python :: 3.10
Classifier: Programming Language :: Python :: 3.11
Classifier: Programming Language :: Python :: 3.12
Classifier: Topic :: Education
Classifier: Topic :: Software Development :: Libraries :: Python Modules
Requires-Python: >=3.7
License-File: LICENSE
Requires-Dist: requests>=2.28.0
Dynamic: author
Dynamic: author-email
Dynamic: classifier
Dynamic: description
Dynamic: description-content-type
Dynamic: home-page
Dynamic: keywords
Dynamic: license-file
Dynamic: project-url
Dynamic: requires-dist
Dynamic: requires-python
Dynamic: summary
